<VAST version="3.0">
  <Ad id="111" sequence="1">
    <Wrapper allowMultipleAds="true">
      <VASTAdTagURI>
        <![CDATA[
          https://raw.githubusercontent.com/jaretpwatkins/kargo/main/vast_example.xml
        ]]>
      </VASTAdTagURI>
      <Creatives>
        <Creative id="111" sequence="1">
          <Linear>
            <Icons>
              <Icon program="Kargo Privacy" width="132" height="26" xPosition="left" yPosition="top">
                    <StaticResource creativeType="image/png">
                      <![CDATA[https://jaretpwatkins.github.io/kargo_pre-roll/TL_264x52.png]]>
                    </StaticResource>
                    <IconClicks> 
                      <IconClickThrough>
                        <![CDATA[ https://kargo.com/privacy ]]> 
                      </IconClickThrough>
                    </IconClicks>
                  </Icon>
              <Icon program="NAME" width="160" height="60" xPosition="left" yPosition="bottom">
                <StaticResource creativeType="image/png">
                  <![CDATA[https://jaretpwatkins.github.io/kargo/Ad_Council.png]]>
                </StaticResource>
              </Icon>
            </Icons>
          </Linear>
        </Creative>
      </Creatives>
    </Wrapper>
  </Ad>
    <Ad id="111-overlay" sequence="2">
     <Wrapper>
       <VASTAdTagURI>
         <![CDATA[
           https://raw.githubusercontent.com/jaretpwatkins/kargo_pre-roll/main/Overlay.xml
         ]]>
       </VASTAdTagURI>
     </Wrapper>
   </Ad>
</VAST>
